Metadata-Version: 2.1
Name: dreem
Version: 0.1.16
Summary: DREEM solves RNA structure ensembles using chemical probing data
Home-page: https://github.com/rouskinlab/dreem
Author: Silvi Rouskin Lab
Author-email: silvi@hms.harvard.edu
Requires-Python: >=3.10
License-File: LICENSE
Requires-Dist: alabaster (==0.7.13)
Requires-Dist: appnope (==0.1.3)
Requires-Dist: argcomplete (==2.0.0)
Requires-Dist: arrow (==1.2.3)
Requires-Dist: asttokens (==2.1.0)
Requires-Dist: async-generator (==1.10)
Requires-Dist: attrs (==22.1.0)
Requires-Dist: autoreload (==0.1.2)
Requires-Dist: babel (==2.11.0)
Requires-Dist: backcall (==0.2.0)
Requires-Dist: binaryornot (==0.4.4)
Requires-Dist: bleach (==5.0.1)
Requires-Dist: blockdiag (==3.0.0)
Requires-Dist: build (==0.9.0)
Requires-Dist: chardet (==5.1.0)
Requires-Dist: charset-normalizer (==3.0.1)
Requires-Dist: click (==8.1.3)
Requires-Dist: click-option-group (==0.5.5)
Requires-Dist: colorlog (==6.7.0)
Requires-Dist: commonmark (==0.9.1)
Requires-Dist: contourpy (==1.0.6)
Requires-Dist: cookiecutter (==2.1.1)
Requires-Dist: cssselect2 (==0.7.0)
Requires-Dist: custom-inherit (==2.4.1)
Requires-Dist: cutadapt (>=4.1)
Requires-Dist: cycler (==0.11.0)
Requires-Dist: debugpy (>=1.6.3)
Requires-Dist: decorator (==5.1.1)
Requires-Dist: distlib (==0.3.6)
Requires-Dist: dms-ci (>=0.1.0)
Requires-Dist: dnaio (==0.10.0)
Requires-Dist: docutils (==0.17.1)
Requires-Dist: editorconfig (==0.12.3)
Requires-Dist: entrypoints (==0.4)
Requires-Dist: enum34 (==1.1.10)
Requires-Dist: exceptiongroup (==1.0.4)
Requires-Dist: executing (==1.2.0)
Requires-Dist: fastqsplitter (==1.2.0)
Requires-Dist: filelock (==3.9.0)
Requires-Dist: fonttools (==4.38.0)
Requires-Dist: funcparserlib (==1.0.1)
Requires-Dist: h11 (==0.14.0)
Requires-Dist: idna (==3.4)
Requires-Dist: imagesize (==1.4.1)
Requires-Dist: importlib-metadata (==6.0.0)
Requires-Dist: iniconfig (==1.1.1)
Requires-Dist: jaraco.classes (==3.2.3)
Requires-Dist: jedi (==0.18.2)
Requires-Dist: jinja2 (==3.1.2)
Requires-Dist: jinja2-time (==0.2.0)
Requires-Dist: joblib (==1.2.0)
Requires-Dist: jsbeautifier (==1.14.7)
Requires-Dist: keyring (==23.13.1)
Requires-Dist: kiwisolver (==1.4.4)
Requires-Dist: llvmlite (==0.39.1)
Requires-Dist: lxml (==4.9.1)
Requires-Dist: markupsafe (==2.1.2)
Requires-Dist: matplotlib (==3.6.2)
Requires-Dist: matplotlib-inline (==0.1.6)
Requires-Dist: more-itertools (==9.0.0)
Requires-Dist: nest-asyncio (==1.5.6)
Requires-Dist: nox (==2022.11.21)
Requires-Dist: numba (==0.56.4)
Requires-Dist: numpy (==1.23.4)
Requires-Dist: outcome (==1.2.0)
Requires-Dist: packaging (==21.3)
Requires-Dist: pandas (==1.5.2)
Requires-Dist: parso (==0.8.3)
Requires-Dist: pep517 (==0.13.0)
Requires-Dist: pexpect (==4.8.0)
Requires-Dist: pickleshare (==0.7.5)
Requires-Dist: pillow (==9.3.0)
Requires-Dist: pip-tools (==6.10.0)
Requires-Dist: pkginfo (==1.9.6)
Requires-Dist: platformdirs (==2.5.4)
Requires-Dist: plotly (==5.11.0)
Requires-Dist: pluggy (==1.0.0)
Requires-Dist: prompt-toolkit (==3.0.33)
Requires-Dist: psutil (==5.9.4)
Requires-Dist: ptyprocess (==0.7.0)
Requires-Dist: pure-eval (==0.2.2)
Requires-Dist: py4j (==0.10.9.5)
Requires-Dist: pyaml (==21.10.1)
Requires-Dist: pyarrow (==10.0.1)
Requires-Dist: pydantic (==1.10.4)
Requires-Dist: pygments (==2.13.0)
Requires-Dist: pyparsing (==3.0.9)
Requires-Dist: pysocks (==1.7.1)
Requires-Dist: pyspark (==3.3.1)
Requires-Dist: pytest (==7.2.0)
Requires-Dist: python-dateutil (==2.8.2)
Requires-Dist: python-slugify (==8.0.1)
Requires-Dist: pytz (==2022.6)
Requires-Dist: pyyaml (==6.0)
Requires-Dist: pyzmq (==24.0.1)
Requires-Dist: readme-renderer (==37.3)
Requires-Dist: recommonmark (==0.7.1)
Requires-Dist: reportlab (==3.6.12)
Requires-Dist: requests (==2.28.2)
Requires-Dist: requests-toolbelt (==0.10.1)
Requires-Dist: rfc3986 (==2.0.0)
Requires-Dist: rich (==13.0.1)
Requires-Dist: scikit-learn (==1.1.3)
Requires-Dist: scipy (==1.9.3)
Requires-Dist: seaborn (==0.12.1)
Requires-Dist: selenium (==4.7.2)
Requires-Dist: six (==1.16.0)
Requires-Dist: sniffio (==1.3.0)
Requires-Dist: snowballstemmer (==2.2.0)
Requires-Dist: sortedcontainers (==2.4.0)
Requires-Dist: sphinx (==4.5.0)
Requires-Dist: sphinx-panels (==0.6.0)
Requires-Dist: sphinx-rtd-theme (==1.1.1)
Requires-Dist: sphinxcontrib-blockdiag (==3.0.0)
Requires-Dist: sphinxcontrib-devhelp (==1.0.2)
Requires-Dist: sphinxcontrib-htmlhelp (==2.0.1)
Requires-Dist: sphinxcontrib-jsmath (==1.0.1)
Requires-Dist: sphinxcontrib-qthelp (==1.0.3)
Requires-Dist: sphinxcontrib-serializinghtml (==1.1.5)
Requires-Dist: sphinx-click (==4.4.0)
Requires-Dist: stack-data (==0.6.1)
Requires-Dist: svglib (==1.4.1)
Requires-Dist: tenacity (==8.1.0)
Requires-Dist: text-unidecode (==1.3)
Requires-Dist: threadpoolctl (==3.1.0)
Requires-Dist: tinycss2 (==1.2.1)
Requires-Dist: tomli (==2.0.1)
Requires-Dist: tornado (==6.2)
Requires-Dist: tqdm (==4.64.1)
Requires-Dist: traitlets (>=5.1)
Requires-Dist: trio (==0.22.0)
Requires-Dist: trio-websocket (==0.9.2)
Requires-Dist: typing-extensions (==4.5.0)
Requires-Dist: urllib3 (==1.26.13)
Requires-Dist: virtualenv (==20.20.0)
Requires-Dist: watchdog (==2.2.0)
Requires-Dist: wcwidth (==0.2.5)
Requires-Dist: webcolors (==1.12)
Requires-Dist: webencodings (==0.5.1)
Requires-Dist: wsproto (==1.2.0)
Requires-Dist: xopen (==1.7.0)
Requires-Dist: zipp (==3.11.0)
